umzz.py
umzz-0.0.33.data/scripts/umzz
umzz-0.0.33.data/scripts/umzz2
umzz-0.0.33.dist-info/LICENSE
umzz-0.0.33.dist-info/METADATA
umzz-0.0.33.dist-info/WHEEL
umzz-0.0.33.dist-info/top_level.txt
umzz-0.0.33.dist-info/RECORD
