Metadata-Version: 2.1
Name: umzz
Version: 0.0.33
Summary: Ultra Mega Zoom Zoom is SCTE-35 Injection for Adaptive Bitrate HLS
Home-page: https://github.com/futzu/umzz
Author: Adrian of Doom
Author-email: a@slow.golf
Platform: all
Classifier: License :: OSI Approved :: MIT License
Classifier: Operating System :: OS Independent
Classifier: Programming Language :: Python :: 3.6
Classifier: Programming Language :: Python :: Implementation :: PyPy
Classifier: Programming Language :: Python :: Implementation :: CPython
Requires-Python: >=3.6
License-File: LICENSE
Requires-Dist: iframes >=0.0.7
Requires-Dist: m3ufu >=0.0.89
Requires-Dist: new-reader >=0.1.9
Requires-Dist: threefive >=2.4.57
Requires-Dist: x9k3 >=0.2.57
